{
  "source_file": "/Users/admin/Downloads/定制产品报价原则.docx",
  "line_count": 2563,
  "sections": [
    {
      "heading": "前言",
      "content": [
        "定制产品报价原则"
      ]
    },
    {
      "heading": "1.柜体",
      "content": [
        "表1"
      ]
    },
    {
      "heading": "450＜柜体进深≤600（衣柜等）（单位：元/投影面积）",
      "content": [
        "材质",
        "拼框门/玻璃门/拱形门/铝框门",
        "真格栅门/新古典格栅门",
        "流云/飞瀑/拉线/藤编/铝框推拉/外悬推拉门",
        "简美",
        "无门有背板",
        "玫瑰木",
        "4980",
        "5180",
        "5380",
        "5180",
        "4580",
        "樱桃木",
        "5480",
        "5680",
        "5880",
        "5680",
        "4880",
        "白蜡木",
        "5480",
        "5680",
        "5880",
        "/",
        "4880",
        "白橡木",
        "6380",
        "6580",
        "6880",
        "6580",
        "5780",
        "黑胡桃木",
        "7380",
        "7780",
        "8680",
        "7780",
        "6580",
        "PS.简美衣柜470＜进深≤620",
        "表2",
        "柜体进深≤450（如书柜，玄关柜等）（单位：元/投影面积）",
        "材质",
        "无门无背板",
        "无门有背板",
        "有门无背板",
        "有门有背板",
        "玫瑰木",
        "2680",
        "3680",
        "3980",
        "4480",
        "樱桃木",
        "2980",
        "4180",
        "4480",
        "4980",
        "白蜡木",
        "2980",
        "4180",
        "4480",
        "4980",
        "白橡木",
        "3880",
        "4980",
        "5580",
        "5880",
        "黑胡桃木",
        "4580",
        "5680",
        "6380",
        "6680",
        "Ps.此处[有门]指拼框门/玻璃门/拱形门/铝框门柜体的单价",
        "表3",
        "柜体进深≤450（单位：元/投影面积）",
        "材质",
        "拼框门/玻璃门/拱形门/铝框门",
        "真格栅门/新古典格栅门",
        "流云/飞瀑/拉线/藤编/铝框推拉/外悬推拉门",
        "玫瑰木",
        "4480",
        "4680",
        "4880",
        "樱桃木",
        "4980",
        "5180",
        "5380",
        "白蜡木",
        "4980",
        "5180",
        "5380",
        "白橡木",
        "5880",
        "6080",
        "6380",
        "黑胡桃木",
        "6680",
        "7080",
        "7980",
        "设计遇见柜体时，价格在表1/2/3基础上+200;海棠柜体：价格在表1/2/3基础上+300",
        "表4",
        "简美书柜进深≤470",
        "材质",
        "无门有背板",
        "有门有背板",
        "玫瑰木",
        "3680",
        "4680",
        "樱桃木",
        "4180",
        "5180",
        "白蜡木",
        "/",
        "/",
        "白橡木",
        "4980",
        "6080",
        "黑胡桃木",
        "5680",
        "7080"
      ]
    },
    {
      "heading": "1.1 *书柜：指进深≤450mm的柜体，简美柜体≤470mm",
      "content": [
        "*衣柜：指450＜进深≤600mm的柜体，简美柜体470＜进深≤620mm",
        "进深尺寸均指产品最大外径尺寸"
      ]
    },
    {
      "heading": "1.2 *超深柜体计价：",
      "content": []
    },
    {
      "heading": "600mm＜柜体进深≤700mm，加价15%；",
      "content": [
        "简美柜体620mm＜柜体进深≤720mm，加价15%；",
        "柜体进深＞700mm,需前后两组柜体组成，价格为前后两组柜体之和。",
        "简美柜体进深＞720mm,需前后两组柜体组成，价格为前后两组柜体之和。"
      ]
    },
    {
      "heading": "1.3 柜体投影面积＜1.6㎡，按照1.6㎡计算。按投影面积计算的柜体，带支腿部分计入投影面积，支腿高度＞150mm的，高度按150mm计算。",
      "content": []
    },
    {
      "heading": "1.4 产品目录中的小件成品标准品家具原则上不做更改，改动较小增加15%，改动较大以该标准产品为基准，按比例计算；如改动尺寸难以取舍，增加15%与按比例计算之间价格取高。",
      "content": []
    },
    {
      "heading": "1.5 定制柜体若存在异形，比如包裹管道、避让拐角，则避让部分的柜体价格上浮30%。",
      "content": [
        "公式=避让部分的正面投影面积*单价*（1+0.3）"
      ]
    },
    {
      "heading": "1.6 平板门（流云/飞瀑）纹路连续不超过0.9米，依然按拼框门计价；反之，超过0.9米，就按平板门计价。",
      "content": []
    },
    {
      "heading": "1.7 餐边柜卡座：不建议做，费料费工不好看，若坚持做，按单体电视柜（非投影面积计价的）报价，长度不足1.6m，按1.6m计算。",
      "content": []
    },
    {
      "heading": "1.8 不同材质的像素格书柜计价方法：",
      "content": [
        "按柜体单价*柜体投影面积+门板投影面积*门板单价计算，门板单价见表11",
        "如：以下柜体"
      ]
    },
    {
      "heading": "1.9 衣柜柜体只门板为不同材质：",
      "content": [
        "公式：柜体单价=拼框门柜体单价+单独柜门差价",
        "*单独柜门差价计算见表11",
        "举例：衣柜，樱桃木柜体，黑胡桃平板柜门。",
        "柜体单价=樱桃木拼框门柜体5480+（黑胡桃平板门板3880-樱桃木拼框门板1780）=5480+2100=7580"
      ]
    },
    {
      "heading": "1.10 柜体非见光面玫瑰木，见光面其余材质：",
      "content": [
        "公式：整柜按外露材质报价降低15%（外露黑胡桃）/10％（外露白橡木）/5%（外露樱桃木/白蜡木）",
        "例如：流云衣柜1.8*0.6*2.2m，见光面黑胡桃，非见光面玫瑰木",
        "价格=1.8*2.2*黑胡桃流云柜体单价8680*(1-0.15)=29216.88",
        "流云衣柜1.8*0.6*2.2m，见光面樱桃木，非见光面玫瑰木",
        "价格=1.8*2.2*樱桃木流云柜体单价5880*(1-0.05)=22120.56"
      ]
    },
    {
      "heading": "1.11 双面门柜体",
      "content": [
        "按投影面积计价，单价如下：",
        "表5"
      ]
    },
    {
      "heading": "450＜柜体进深≤600（单位：元/投影面积）",
      "content": [
        "拼框/",
        "格栅",
        "拼框/",
        "平板",
        "格栅/",
        "平板",
        "拼框/",
        "拼框",
        "格栅/",
        "格栅",
        "平板/",
        "平板",
        "玫瑰木",
        "6360",
        "6760",
        "6960",
        "6160",
        "6560",
        "7160",
        "樱桃木",
        "6900",
        "7300",
        "7500",
        "6700",
        "7100",
        "7700",
        "白蜡木",
        "6900",
        "7300",
        "7500",
        "6700",
        "7100",
        "7700",
        "白橡木",
        "7960",
        "8500",
        "8760",
        "7760",
        "8180",
        "9060",
        "黑胡桃",
        "9810",
        "10410",
        "10810",
        "9510",
        "10210",
        "11710",
        "柜体进深≤450（单位：元/投影面积）",
        "拼框/",
        "格栅",
        "拼框/",
        "平板",
        "格栅/",
        "平板",
        "拼框/",
        "拼框",
        "格栅/",
        "格栅",
        "平板/",
        "平板",
        "玫瑰木",
        "5860",
        "6260",
        "6460",
        "5660",
        "6060",
        "6660",
        "樱桃木",
        "6400",
        "6800",
        "7000",
        "6200",
        "6600",
        "7200",
        "白蜡木",
        "6400",
        "6800",
        "7000",
        "6200",
        "6600",
        "7200",
        "白橡木",
        "7400",
        "7960",
        "8180",
        "7180",
        "7660",
        "8500",
        "黑胡桃",
        "9110",
        "9710",
        "10110",
        "8810",
        "9510",
        "11010",
        "P.S.",
        "拼框指：拼框门/玻璃门/拱形门/铝框门",
        "格栅指：真格栅门/新古典格栅门",
        "平板指：流云/飞瀑/简美/拉线/藤编/铝框推拉/外悬条条推拉"
      ]
    },
    {
      "heading": "1.12 操作空区或电视柜空区等带背板区域价格",
      "content": [
        "按面积计算，单价：",
        "表6",
        "材质",
        "价格（元/投影面积）",
        "玫瑰木",
        "1235",
        "樱桃木",
        "1326",
        "白蜡木",
        "1326",
        "白橡木/发光背板",
        "1630",
        "黑胡桃",
        "2002",
        "单独发光背板单价为1630/平米，定制图案每平米+200；"
      ]
    },
    {
      "heading": "1.13 钻石柜报价：",
      "content": [
        "如上图，若钻石柜体部分与其他柜体为同类型（均为开放/带门），可按“对应长度*高度*对应柜体单价”计算，以开放柜体玫瑰木为例：[3.04+（2.184-0.35）]*2.3*3680",
        "如上图,若钻石柜体部分不与其他柜体同类型（钻石柜为开放，其他为带门），按“标注出的长度*高度*对应柜体单价”计算，计入组合柜体中，以玫瑰木为例：[0.63+（0.7-0.35）]*2.3*3680"
      ]
    },
    {
      "heading": "1.14 无底板柜/冰箱柜",
      "content": [
        "上部柜体按照柜体投影面积计算",
        "下部侧板按照侧板面积计算，单价如下：",
        "表7",
        "材质",
        "价格（元/投影面积）",
        "玫瑰木",
        "1100",
        "樱桃木",
        "1180",
        "白蜡木",
        "1180",
        "白橡木",
        "1480",
        "黑胡桃",
        "1800",
        "以下图为例：",
        "上柜：0.94*0.5*7380*1.15=3988.89",
        "(拼框门衣柜单价）（600mm＜柜体进深≤700mm,加价15%；）",
        "下侧板：1.85*0.65*1800*2=4329",
        "总价：3988.89+4329=8317.89"
      ]
    },
    {
      "heading": "1.15 常规柜框+美式门板/美式抽屉柜体价格计算方法",
      "content": [
        "普通柜框+美式门美式抽屉",
        "按美式柜体单价*柜体投影面积，遵循一延米送2个抽屉，超出的抽屉按美式抽屉单个加价",
        "普通柜框+美式抽屉",
        "普通柜体单价*柜体投影面积，遵循一延米送2个抽屉,但需要加上(美式抽屉-普通抽屉)差价*赠送数量，再单独加上超出的美式抽屉数量*价格",
        "美式抽屉价格如下：",
        "表8",
        "材质",
        "价格（元/个）",
        "玫瑰木",
        "360",
        "樱桃木",
        "480",
        "白蜡木",
        "480",
        "白橡木",
        "528",
        "黑胡桃",
        "720",
        "例如：拼框门黑胡桃材质，长度2米高度为2.4米的普通柜框衣柜，且有四个美式抽屉：7380*2.4*2+（720-600）*4；五个美式抽屉：7380*2.4*2+（720-600）*4+720",
        "普通柜框+美式门",
        "美式柜体单价*柜体投影面积"
      ]
    },
    {
      "heading": "1.16 天地铰链铝框门+平板门计算方法",
      "content": [
        "因门厚不一，设计类似于上图结构的铝框门使用天地铰链时，其他门型需对齐门厚，平板门纹理连续超过0.9m时，平板门部分需加价15%"
      ]
    },
    {
      "heading": "1.17 岛台价格",
      "content": [
        "标准品价格包含电力轨道、2个活动插座、洞洞板、岩板，删减配件不减钱，尺寸不变动，格局变动（如将柜门改为开放格/将抽屉改为柜门）价格不变，在此基础上额外增加配件按常规规则执行（如额外增加抽屉，则按个收费/额外增加活动插座，按个收费）",
        "定制价格：",
        "以标准品为基础，按比例计算，以修改后的长边为投影面，如图中红色圆框区域，以左一为例：白蜡木价格为12380/1.2*0.9=9285元"
      ]
    },
    {
      "heading": "2. 部件",
      "content": []
    },
    {
      "heading": "2.1 抽屉/挡边条/灯带",
      "content": [
        "表9",
        "材质",
        "抽屉/个",
        "挡边条/米",
        "灯带/米",
        "玫瑰木",
        "300",
        "220",
        "300",
        "樱桃木",
        "400",
        "260",
        "白蜡木",
        "400",
        "260",
        "白橡木",
        "440",
        "320",
        "黑胡桃",
        "600",
        "350",
        "P.S."
      ]
    },
    {
      "heading": "1）抽屉每米赠送2个，超出按个加钱",
      "content": []
    },
    {
      "heading": "2）关于书柜抽屉：",
      "content": [
        "①部分无门部分有门书柜，抽屉面积算入无门；",
        "②全带门书柜，抽屉算入有门书柜。",
        "③卡座书柜卡座部分，进深＞450mm按平板门衣柜价格计算，进深＞600mm时，参照“超深柜体”计价"
      ]
    },
    {
      "heading": "3）挡边条按投影面积计价，单价随实际柜体单价。",
      "content": [
        "此表格挡边条单价仅为指导价，用于客户认为挡边条按投影计价太贵时使用。"
      ]
    },
    {
      "heading": "2.2 书梯",
      "content": [
        "书梯按米计价，价格为书梯总长*单价，分为不可回收书梯与可回收书梯，对应常规轨道与可回收梯轨道；",
        "轨道按米计价，价格为长度*单价，轨道分为常规轨道与可回收梯轨道，轨道单价不同，详见下表：",
        "表10",
        "材质",
        "木质梯(元/m)",
        "常规轨道",
        "可回收轨道",
        "玫瑰木",
        "559",
        "300",
        "380",
        "樱桃木",
        "585",
        "白蜡木",
        "585",
        "白橡木",
        "715",
        "黑胡桃",
        "858"
      ]
    },
    {
      "heading": "2.3门板",
      "content": [
        "表内为投影面积单价：",
        "表11",
        "材质",
        "玻璃屏风",
        "屏风/樟纸门",
        "单独拼框门/玻璃门/拱形门",
        "单独铝框门",
        "单独真格栅门/新古典格栅门",
        "单独流云/飞瀑/简美/拉线/藤编/外悬条条推拉门",
        "玫瑰木",
        "660",
        "1380",
        "1680",
        "1380",
        "1880",
        "2280",
        "樱桃木",
        "860",
        "1480",
        "1780",
        "1980",
        "2380",
        "白蜡木",
        "860",
        "1480",
        "1780",
        "1980",
        "2380",
        "白橡木",
        "960",
        "1780",
        "2080",
        "2280",
        "2980",
        "黑胡桃",
        "1080",
        "2580",
        "2980",
        "3280",
        "3880",
        "PS.",
        "不单独做门板，门板单价仅供计算某些特殊柜体时使用。",
        "吊轨门价格在门板基础上+400元:门板单价*门板面积+400。",
        "屏风/樟纸门投影面积不足1.6㎡，按1.6㎡计算。",
        "拼框门包括：经典门、胶囊门",
        "玻璃门包括：拼框玻璃门、拱形玻璃门、胶囊玻璃门"
      ]
    },
    {
      "heading": "2.4 背板",
      "content": [
        "非整体小面积，比如餐边柜，电视背景柜正面空区外露，不用单独增加，按对应规则“1.12” 计价即可；",
        "常规结构背板外露（不区分是否平装）：柜体总价加10%",
        "例：1.8*0.6*2.2黑胡桃木流云衣柜背板外露平装",
        "价格：1.8*2.2*8680*1.1=37810.08元"
      ]
    },
    {
      "heading": "2.5 柜内茶格",
      "content": [
        "指柜内放置茶具的小茶格，不区分能否活动，如下图：",
        "价格均按照：",
        "体积*单价 计算",
        "体积为 茶格的整体体积，如下图：",
        "体积=a*b*c",
        "单价：",
        "表12",
        "材质",
        "单价（元/m³）",
        "玫瑰木",
        "9150",
        "樱桃木",
        "9710",
        "白蜡木",
        "9710",
        "白橡木",
        "11720",
        "黑胡桃",
        "13880"
      ]
    },
    {
      "heading": "2.6 拱形玄关挡板",
      "content": [
        "指弧形造型挡板位置，红框部分按照平板门柜体价格计算=柜体长*挡板最低点到柜体顶部高度*平板门柜体单价，绿框位置由柜体减去红框面积后正常计算；"
      ]
    },
    {
      "heading": "2.7 圆弧侧板",
      "content": [
        "圆弧侧板价格按米计算，每根长度300元/米"
      ]
    },
    {
      "heading": "3.配件",
      "content": []
    },
    {
      "heading": "3.1轨道插座单独计价：",
      "content": [
        "T25:",
        "电力轨道500元/米",
        "活动插座：五孔100元/个、USB插口120元/个",
        "西蒙："
      ]
    },
    {
      "heading": "0.5M轨道(不含适配器)208元",
      "content": []
    },
    {
      "heading": "0.8M轨道(不含适配器)356元",
      "content": []
    },
    {
      "heading": "1M轨道配(不含适配器)446元",
      "content": [
        "活动插座：五孔58元/个、A+C双口106元/个"
      ]
    },
    {
      "heading": "3.2岩板：",
      "content": [
        "岩板台面，背板1460元/米；铝框岩板门板1860元/米",
        "岩板台面：1460*岩板长度+柜体正常计算",
        "铝框岩板门板：1860*岩板长度+无门（有背板/无背板）柜体价格",
        "岩板背板：1460*岩板长度；空区处，高度＜55cm不计算侧板价格，",
        "高度≥55cm时，按照超出侧板面积*单价计算",
        "侧板",
        "材质",
        "（单位：元/投影面积）",
        "玫瑰木",
        "1500",
        "樱桃木",
        "1538",
        "白蜡木",
        "1538",
        "白橡木",
        "1748",
        "黑胡桃",
        "2028"
      ]
    },
    {
      "heading": "3.3金属洞洞板",
      "content": []
    },
    {
      "heading": "840元/平米",
      "content": []
    },
    {
      "heading": "3.4铜套脚",
      "content": []
    },
    {
      "heading": "100元/个（不区分大小）",
      "content": []
    },
    {
      "heading": "3.5箱体床举升器",
      "content": [
        "电动举升器（承重100kg）在原价格基础上增加1000元，",
        "小蜻蜓举升器：当W＞1800时默认使用两套，在原价格基础上增加600元。"
      ]
    },
    {
      "heading": "3.6拉手",
      "content": [
        "《设计标准手册》中未列出的特殊木拉手，收费100元/个，不区分材质。"
      ]
    },
    {
      "heading": "3.7抽屉内做收纳格",
      "content": [
        "在原基础上加价：玫瑰木150元/白蜡木200元/樱桃木200元/白橡木220元/黑胡桃木300元/组，不区分格数。"
      ]
    },
    {
      "heading": "3.8按弹抽屉：使用推弹阻尼回收滑轨，收费850元/套。",
      "content": []
    },
    {
      "heading": "3.9灯带多个开关分区控制：灯带正常计算，每增加一个分区开关，增加400元；",
      "content": [
        "一个区域多个开关，灯带正常计算，每增加一个开关，增加100元。"
      ]
    },
    {
      "heading": "3.10脚轮：合金支架 288元/4个",
      "content": []
    },
    {
      "heading": "3.11穿衣镜",
      "content": [
        "推拉镜：",
        "规格",
        "900mm",
        "1100mm",
        "1200mm",
        "价格",
        "280元",
        "320元",
        "350元",
        "门后隐形穿衣镜：280元/个"
      ]
    },
    {
      "heading": "4. 床",
      "content": []
    },
    {
      "heading": "4.1 拼色床，如拼色部分很少，不涉及结构位置，如床腿和大面积床头，只是作为点缀，价格不变；",
      "content": []
    },
    {
      "heading": "4.2 不同尺寸床报价逻辑：",
      "content": [
        "床垫宽度上：1.2米及以下，价格同1.2米；1.35米以上按1.5米算；",
        "床垫长度上：1.9米长也同2米的。",
        "原因：尺寸虽不同，但用料，工艺都是一样的。比如1.2米和1米的床，开料都是需要按1.2米的料开的"
      ]
    },
    {
      "heading": "4.3 标品无1.2米价格的：",
      "content": []
    },
    {
      "heading": "1.2米床=1.5米-（1.8米-1.5米）",
      "content": []
    },
    {
      "heading": "4.4 超大床价格",
      "content": [
        "超大床价格以该床1.5m宽价格为基础，按比例计算。",
        "如：",
        "计算经典箱体床黑胡桃木2*2m床价格："
      ]
    },
    {
      "heading": "12800/1.5*2=17066元",
      "content": [
        "计算经典箱体床樱桃木2*2.2m价格："
      ]
    },
    {
      "heading": "8200/1.5*2.2=12026元",
      "content": []
    },
    {
      "heading": "4.5箱体床加高/架式床加高",
      "content": [
        "架式床不区分加高高度，床体高度尺寸改动均按照加整床价格15%计算",
        "4.6",
        "表13",
        "部件",
        "材质",
        "排骨架换平板拼框床板",
        "无床头架式床/箱体床（塌式床）",
        "玫瑰木",
        "+800",
        "-1200",
        "樱桃木",
        "+1200",
        "-1600",
        "白蜡木",
        "+1200",
        "-1600",
        "白橡木",
        "+1360",
        "-1600",
        "黑胡桃",
        "+1600",
        "-2000"
      ]
    },
    {
      "heading": "4.7 床头板加宽：（如下图）",
      "content": [
        "表14",
        "加宽尺寸X(mm)",
        "X≤100"
      ]
    },
    {
      "heading": "100＜X≤150",
      "content": []
    },
    {
      "heading": "150＜X≤200",
      "content": [
        "床垫宽度(mm)",
        "1800",
        "1500",
        "1200",
        "1800",
        "1500",
        "1200",
        "1800",
        "1500",
        "1200",
        "玫瑰木",
        "358",
        "299",
        "239",
        "537",
        "448",
        "358",
        "716",
        "597",
        "478",
        "樱桃木",
        "365",
        "305",
        "244",
        "548",
        "457",
        "365",
        "731",
        "609",
        "487",
        "白蜡木",
        "365",
        "305",
        "244",
        "548",
        "457",
        "365",
        "731",
        "609",
        "487",
        "白橡木",
        "468",
        "389",
        "311",
        "700",
        "585",
        "468",
        "935",
        "778",
        "622",
        "黑胡桃",
        "567",
        "473",
        "378",
        "851",
        "709",
        "567",
        "1134",
        "945",
        "756"
      ]
    },
    {
      "heading": "4.8儿童床非标品按非标儿童床报价方案执行。",
      "content": [
        "儿童高架床：以下图为例床垫尺寸:1.2*2m，高度与标准上下床一致",
        "表15",
        "材质",
        "挂梯",
        "梯柜",
        "玫瑰木",
        "7762",
        "9952",
        "樱桃木",
        "9030",
        "12840",
        "白蜡木",
        "9030",
        "12840",
        "白橡木",
        "11258",
        "16008",
        "黑胡桃",
        "13824",
        "19504"
      ]
    },
    {
      "heading": "4.9 榻榻米",
      "content": [
        "表16",
        "榻榻米（单位：元/投影平米）",
        "材质",
        "高度≤400mm"
      ]
    },
    {
      "heading": "400＜高度≤500",
      "content": []
    },
    {
      "heading": "500＜高度≤550",
      "content": []
    },
    {
      "heading": "550＜高度≤600",
      "content": [
        "玫瑰木",
        "3180",
        "3980",
        "4280",
        "4980",
        "樱桃木",
        "3680",
        "4480",
        "4780",
        "5480",
        "白蜡木",
        "3680",
        "4480",
        "4780",
        "5480",
        "白橡木",
        "4480",
        "5480",
        "5800",
        "6380",
        "黑胡桃",
        "5580",
        "6680",
        "7080",
        "7380"
      ]
    },
    {
      "heading": "4.10抽屉床：（如下图）",
      "content": [
        "对应尺寸箱体床价格+抽屉个数*抽屉单价",
        "如上图：1.2m樱桃木箱体床7600+3*400=8800元"
      ]
    },
    {
      "heading": "4.11 榻榻米+超大抽屉：榻榻米投影面积+抽屉个数*抽屉单价",
      "content": []
    },
    {
      "heading": "5. 桌子",
      "content": []
    },
    {
      "heading": "5.1 桌类标准尺寸标准价格，岩板与非岩板相同。难度较大的非良禽样式订制的桌类，在标品基础价格上加价15%。",
      "content": []
    },
    {
      "heading": "5.2 非标尺寸桌类价格上只看长度，2米以下，非标的往现有的高的靠，1.2米以下按1.2米价格计算，以此类推。长度2米以上，以2米桌子为基础，按比例计价。",
      "content": [
        "进深上≤900mm不影响价格，进深＞900mm按两张桌子计算，高度不影响价格。",
        "例如，1300*450mm/1300*900mm的，都按1400*750mm的价格。"
      ]
    },
    {
      "heading": "800*600mm/600*600mm的，都按1000*600mm的价格。",
      "content": []
    },
    {
      "heading": "5.3 带屉餐桌及带屉书桌价格以无屉餐桌价格为基准，增加抽屉价格",
      "content": []
    },
    {
      "heading": "5.4 非标尺寸挂墙桌定制报价规则(以桌面长度为尺寸依据)：",
      "content": []
    },
    {
      "heading": "600 以下按 600 计价；",
      "content": []
    },
    {
      "heading": "600-1800，非标的往高的靠；",
      "content": []
    },
    {
      "heading": "1800以上，以2400为基础，按比例计价；",
      "content": []
    },
    {
      "heading": "2400以上分2个桌子计算",
      "content": [
        "表17",
        "挂墙桌",
        "材质",
        "长度600mm",
        "长度1000mm",
        "长度1200mm",
        "长度1600mm",
        "长度1800mm",
        "长度2400mm",
        "玫瑰木",
        "1500",
        "2000",
        "2600",
        "3700",
        "4830",
        "7410",
        "樱桃木",
        "1750",
        "2350",
        "2950",
        "4250",
        "5790",
        "8890",
        "白蜡木",
        "1750",
        "2350",
        "2950",
        "4250",
        "5790",
        "8890",
        "白橡木",
        "1950",
        "2700",
        "3400",
        "4850",
        "6600",
        "10140",
        "黑胡桃",
        "2250",
        "3150",
        "3950",
        "5650",
        "7900",
        "12170",
        "*注意：飘窗抽拉台面价格按照挂墙桌计算，若抽拉台面不需要抽屉，价格减去（抽屉数量*价格）即可"
      ]
    },
    {
      "heading": "5.5 订制书桌柜，分两部分报价：",
      "content": [
        "①书桌部分报价：正常按书桌价格计算",
        "②书柜部分报价：按照带门或者不带门计算报价，在投影面积小于1.6㎡的情况下，加价15%，大于1.6㎡则不增加。"
      ]
    },
    {
      "heading": "5.6 转角书桌",
      "content": [
        "以长边方向为A，短边减长边宽度为B",
        "转角部分较小，A+B≤2米时，标准尺寸按标准价格，非标的往现有的高的靠。",
        "如下图：1500+(900-500)=1900，则按2000mm桌子价格报价",
        "(示意图仅展示尺寸，不做分段位置区分）",
        "转角部分较大，A+B＞2米时，按2个桌子计价，其中单个尺寸如果非标则往现有的高的靠，标准的按标准价格。",
        "如下图：1600+900=2500＞2000，则按照1600桌子和1000桌子报价。",
        "(示意图仅展示尺寸，不做分段位置区分）"
      ]
    },
    {
      "heading": "6.其他单品",
      "content": []
    },
    {
      "heading": "6.1 标品电视柜多加抽屉，按个收费",
      "content": []
    },
    {
      "heading": "6.2 悬空挂墙层板价格",
      "content": [
        "表18",
        "材质",
        "价格（元/米）",
        "备注",
        "玫瑰木",
        "780",
        "不区分进深，以长度计算",
        "樱桃木",
        "800",
        "白蜡木",
        "800",
        "白橡木",
        "980",
        "黑胡桃",
        "1100"
      ]
    },
    {
      "heading": "6.3沙发",
      "content": [
        "表19",
        "沙发1",
        "沙发2",
        "标准沙发（经典/小强/抛物线）",
        "单人",
        "双人",
        "三人",
        "SF-05",
        "长滩沙发",
        "SF-06长滩沙发Y",
        "玫瑰木",
        "2800",
        "3600",
        "5400",
        "玫瑰木",
        "8650",
        "9650",
        "樱桃木",
        "3200",
        "4600",
        "6400",
        "樱桃木",
        "9850",
        "10850",
        "白蜡木",
        "3200",
        "4600",
        "6400",
        "白蜡木",
        "9850",
        "10850",
        "白橡木",
        "3500",
        "5000",
        "7000",
        "白橡木",
        "11650",
        "12650",
        "黑胡桃",
        "4200",
        "6000",
        "8000",
        "黑胡桃",
        "13650",
        "14650",
        "罗汉床/榻报价：同尺寸沙发1价格增加30%",
        "表20",
        "新款沙发垫",
        "单人",
        "双人",
        "三人",
        "经典/抛物线/小强沙发(布艺)）",
        "480",
        "960",
        "1440",
        "经典/抛物线/小强沙发",
        "(接触面真皮)）",
        "1170",
        "2340",
        "3510",
        "长滩沙发(布艺)",
        "/",
        "/",
        "1950",
        "长滩沙发(接触面真皮)",
        "/",
        "/",
        "4270"
      ]
    },
    {
      "heading": "7.部分产品目录标品价格",
      "content": []
    },
    {
      "heading": "7.1床头柜",
      "content": [
        "编号",
        "名称",
        "图纸",
        "边角",
        "长/m",
        "宽/m",
        "高/m",
        "玫瑰木",
        "樱桃木",
        "白蜡木",
        "白橡木",
        "黑胡桃",
        "CTG-01",
        "经典床头柜1",
        "圆角圆边",
        "0.45",
        "0.4",
        "0.5",
        "1480",
        "1780",
        "1780",
        "2080",
        "2580",
        "CTG-03",
        "经典床头柜3",
        "圆角圆边",
        "0.45",
        "0.4",
        "0.5",
        "1480",
        "1780",
        "1780",
        "2080",
        "2580",
        "CTG-04",
        "简美床头柜",
        "美式",
        "0.6",
        "0.45",
        "0.6",
        "2180",
        "2480",
        "/",
        "3080",
        "3580",
        "CTG-05",
        "简美三抽床头柜",
        "美式",
        "0.8",
        "0.5",
        "0.6",
        "2980",
        "3480",
        "/",
        "4380",
        "4980"
      ]
    },
    {
      "heading": "7.2 几案",
      "content": [
        "编号",
        "名称",
        "图纸",
        "长/m",
        "宽/m",
        "高/m",
        "玫瑰木",
        "樱桃木",
        "白蜡木",
        "白橡木",
        "黑胡桃",
        "CJ-01",
        "经典茶几",
        "1.20",
        "0.60",
        "0.46",
        "3480",
        "4280",
        "4280",
        "4780",
        "5680",
        "CJ-02",
        "飘飘家的茶几",
        "1.20",
        "0.60",
        "0.46",
        "3480",
        "4280",
        "4280",
        "4780",
        "5680",
        "CJ-04",
        "新现代方几",
        "1.20",
        "1.20",
        "0.46",
        "5980",
        "7180",
        "7180",
        "8380",
        "9980",
        "CJ-06",
        "简美茶几",
        "1.20",
        "0.65",
        "0.46",
        "4580",
        "4920",
        "4920",
        "5680",
        "6480",
        "CJ-07",
        "新现代小方几",
        "0.50",
        "0.50",
        "0.46",
        "1780",
        "3000",
        "3000",
        "3300",
        "3800",
        "CJ-08",
        "杂志柜",
        "0.46",
        "0.28",
        "0.78",
        "960",
        "1080",
        "1080",
        "1380",
        "1680",
        "CJ-09",
        "圆圆几",
        "0.60",
        "0.60",
        "0.46",
        "1100",
        "1280",
        "1280",
        "1380",
        "1580",
        "CJ-10",
        "鹅卵石茶几",
        "0.50",
        "0.35",
        "0.40",
        "500",
        "580",
        "580",
        "680",
        "760",
        "0.65",
        "0.49",
        "0.46",
        "750",
        "820",
        "820",
        "1000",
        "1100"
      ]
    },
    {
      "heading": "7.3 斗柜",
      "content": [
        "编号",
        "名称",
        "图纸",
        "边角",
        "长/m",
        "宽/m",
        "高/m",
        "玫瑰木",
        "樱桃木",
        "白蜡木",
        "白橡木",
        "黑胡桃",
        "DG-01",
        "经典八斗柜",
        "圆角圆边",
        "1.80",
        "0.42",
        "0.80",
        "7880",
        "8480",
        "8480",
        "10580",
        "12980",
        "DG-02",
        "经典五斗柜",
        "圆角圆边",
        "0.80",
        "0.43",
        "1.10",
        "4980",
        "6380",
        "6380",
        "7480",
        "8480",
        "DG-04",
        "简美七斗柜",
        "美式",
        "1.50",
        "0.45",
        "0.90",
        "8280",
        "9880",
        "/",
        "11000",
        "13800",
        "DG-05",
        "简美五斗柜",
        "美式",
        "0.80",
        "0.45",
        "1.10",
        "5580",
        "6880",
        "/",
        "7880",
        "8680",
        "DG-06",
        "经典六斗柜",
        "圆角内斜边",
        "1.10",
        "0.42",
        "0.80",
        "6080",
        "6880",
        "6880",
        "8780",
        "10780",
        "DG-07",
        "落地五斗柜",
        "圆角圆边",
        "0.80",
        "0.42",
        "1.10",
        "5380",
        "5980",
        "5980",
        "7480",
        "8480",
        "DG-08",
        "高腿五斗柜",
        "直角侧圆边",
        "0.80",
        "0.42",
        "1.20",
        "5380",
        "5980",
        "5980",
        "7480",
        "8480",
        "直角侧圆边",
        "0.80",
        "0.42",
        "1.20",
        "5780",
        "6380",
        "6380",
        "7880",
        "8880",
        "DG-09",
        "简美多功能斗柜",
        "美式",
        "1.80",
        "0.45",
        "0.72",
        "7880",
        "9680",
        "/",
        "11000",
        "13800",
        "DG-10",
        "糖果五斗柜",
        "圆角圆边",
        "0.60",
        "0.42",
        "1.175",
        "4680",
        "5980",
        "5980",
        "7480",
        "8480",
        "DG-11",
        "移动收纳柜",
        "圆边圆角",
        "0.45",
        "0.40",
        "0.51",
        "1800",
        "2180",
        "2180",
        "2500",
        "2800",
        "圆边圆角",
        "0.45",
        "0.40",
        "0.61",
        "2160",
        "2380",
        "2380",
        "2960",
        "3360",
        "DG-12",
        "移动收纳柜X",
        "圆边圆角",
        "0.45",
        "0.40",
        "0.51",
        "1800",
        "2180",
        "2180",
        "2500",
        "2800",
        "圆边圆角",
        "0.45",
        "0.40",
        "0.61",
        "2160",
        "2380",
        "2380",
        "2960",
        "3360"
      ]
    },
    {
      "heading": "7.4餐桌",
      "content": [
        "编号",
        "名称",
        "图片",
        "长/m",
        "宽/m",
        "高/m",
        "玫瑰木",
        "樱桃木",
        "白蜡木",
        "白橡木",
        "黑胡桃",
        "CZ-01",
        "罗胖餐桌",
        "1.20",
        "0.70",
        "0.78",
        "3500",
        "3800",
        "3800",
        "4380",
        "4980",
        "1.40",
        "0.75",
        "4000",
        "4500",
        "4500",
        "5480",
        "5980",
        "1.60",
        "0.80",
        "4500",
        "5000",
        "5000",
        "6380",
        "7980",
        "1.80",
        "0.90",
        "5000",
        "6000",
        "6000",
        "7700",
        "9800",
        "2.00",
        "0.90",
        "6000",
        "7500",
        "7500",
        "8900",
        "12800",
        "CZ-02",
        "斜腿餐桌",
        "1.20",
        "0.70",
        "0.78",
        "3500",
        "3800",
        "3800",
        "4380",
        "4980",
        "1.40",
        "0.75",
        "4000",
        "4500",
        "4500",
        "5480",
        "5980",
        "1.60",
        "0.80",
        "4500",
        "5000",
        "5000",
        "6380",
        "7980",
        "1.80",
        "0.90",
        "5000",
        "6000",
        "6000",
        "7680",
        "9800",
        "2.00",
        "0.90",
        "6000",
        "7500",
        "7500",
        "9000",
        "12800",
        "CZ-05",
        "经典圆餐桌",
        "1.00",
        "1.00",
        "0.78",
        "3500",
        "4200",
        "4200",
        "5780",
        "6380",
        "1.20",
        "1.20",
        "4000",
        "4800",
        "4800",
        "6780",
        "7280",
        "CZ-06",
        "简美大桌",
        "1.60",
        "0.80",
        "0.78",
        "4980",
        "5680",
        "5680",
        "6980",
        "8280",
        "1.80",
        "0.90",
        "5680",
        "6780",
        "6780",
        "7980",
        "9580",
        "2.00",
        "0.90",
        "6680",
        "7780",
        "7780",
        "9380",
        "11180",
        "CZ-07",
        "岩板餐桌",
        "1.20",
        "0.70",
        "0.78",
        "3680",
        "3880",
        "3880",
        "4280",
        "4680",
        "1.40",
        "0.75",
        "4280",
        "4480",
        "4480",
        "4880",
        "5280",
        "1.60",
        "0.80",
        "5180",
        "5380",
        "5380",
        "5880",
        "6380",
        "1.80",
        "0.90",
        "6780",
        "7080",
        "7080",
        "7780",
        "8380",
        "2.00",
        "0.90",
        "7380",
        "7680",
        "7680",
        "8380",
        "8980",
        "CZ-08",
        "罗胖带屉餐桌",
        "1.60",
        "0.80",
        "0.78",
        "6300",
        "7400",
        "7400",
        "9180",
        "11580",
        "1.80",
        "0.90",
        "6800",
        "8400",
        "8400",
        "10380",
        "13400",
        "2.00",
        "0.90",
        "7800",
        "9900",
        "9900",
        "11680",
        "16400",
        "CZ-09",
        "罗胖高屉餐桌",
        "1.60",
        "0.80",
        "0.78",
        "6300",
        "7400",
        "7400",
        "9180",
        "11580",
        "1.80",
        "0.90",
        "6800",
        "8400",
        "8400",
        "10380",
        "13400",
        "2.00",
        "0.90",
        "7800",
        "9900",
        "9900",
        "11680",
        "16400",
        "CZ-10",
        "圆圆桌",
        "1.00",
        "1.00",
        "0.78",
        "3200",
        "3480",
        "3480",
        "4180",
        "4780",
        "1.20",
        "1.20",
        "3800",
        "4180",
        "4180",
        "4980",
        "5780",
        "CZ-11",
        "可拆装小长滩",
        "1.20",
        "0.70",
        "0.78",
        "2780",
        "2980",
        "2980",
        "3960",
        "4760",
        "1.40",
        "0.75",
        "2980",
        "3280",
        "3280",
        "4360",
        "5180",
        "1.60",
        "0.80",
        "3480",
        "3680",
        "3680",
        "4880",
        "5880",
        "1.80",
        "0.90",
        "4380",
        "4680",
        "4680",
        "6180",
        "7380",
        "2.00",
        "0.90",
        "4780",
        "5080",
        "5080",
        "6780",
        "8080",
        "2.20",
        "0.90",
        "5080",
        "5480",
        "5480",
        "7260",
        "8680",
        "2.40",
        "0.90",
        "6280",
        "6680",
        "6680",
        "8860",
        "10580",
        "CZ-12",
        "海棠桌",
        "1.40",
        "0.80",
        "0.78",
        "5080",
        "5280",
        "5280",
        "6180",
        "6880",
        "1.60",
        "0.80",
        "5580",
        "5780",
        "5780",
        "6680",
        "7380",
        "1.80",
        "0.90",
        "6980",
        "7180",
        "7180",
        "8280",
        "9080",
        "2.00",
        "0.90",
        "7480",
        "7680",
        "7680",
        "8880",
        "9780",
        "海棠桌      （木质桌面）",
        "1.40",
        "0.80",
        "4280",
        "4880",
        "4880",
        "6280",
        "6980",
        "1.60",
        "0.80",
        "4680",
        "5280",
        "5280",
        "6780",
        "7880",
        "1.80",
        "0.90",
        "5680",
        "5880",
        "5880",
        "8280",
        "9280",
        "2.00",
        "0.90",
        "5980",
        "6480",
        "6480",
        "9180",
        "9980"
      ]
    },
    {
      "heading": "7.5书桌",
      "content": [
        "编号",
        "名称",
        "图片",
        "长/m",
        "宽/m",
        "高/m",
        "玫瑰木",
        "樱桃木",
        "白蜡木",
        "白橡木",
        "黑胡桃",
        "SZ-15",
        "升降桌",
        "1.2",
        "0.6",
        "620-1270",
        "4180",
        "4480",
        "4480",
        "4880",
        "5180",
        "1.4",
        "0.6",
        "620-1270",
        "4480",
        "4780",
        "4780",
        "5180",
        "5680",
        "1.6",
        "0.7",
        "620-1270",
        "4980",
        "5380",
        "5380",
        "5880",
        "6480",
        "1.8",
        "0.8",
        "620-1270",
        "5580",
        "6180",
        "6180",
        "6780",
        "7480",
        "2",
        "0.8",
        "620-1270",
        "5980",
        "6580",
        "6580",
        "7180",
        "7980",
        "SZ-16",
        "带屉升降桌",
        "1.6",
        "0.7",
        "620-1270",
        "6080",
        "6580",
        "6580",
        "7380",
        "8180",
        "1.8",
        "0.8",
        "620-1270",
        "6980",
        "7580",
        "7580",
        "8580",
        "9780",
        "2",
        "0.8",
        "620-1270",
        "7480",
        "7980",
        "7980",
        "9280",
        "10480",
        "SZ-17",
        "长滩岛",
        "2.40",
        "1.00",
        "0.78",
        "12500",
        "13800",
        "/",
        "/",
        "18800",
        "2.40",
        "0.90",
        "0.78",
        "11800",
        "13000",
        "/",
        "/",
        "17600",
        "2.20",
        "0.90",
        "0.78",
        "11400",
        "12600",
        "/",
        "/",
        "16800",
        "2.00",
        "0.90",
        "0.78",
        "10700",
        "11800",
        "/",
        "/",
        "15900",
        "1.80",
        "0.90",
        "0.78",
        "7800",
        "9700",
        "/",
        "/",
        "14800",
        "长滩岛Y",
        "2.40",
        "1.00",
        "0.78",
        "13500",
        "14800",
        "/",
        "/",
        "19800",
        "2.40",
        "0.90",
        "0.78",
        "12800",
        "14000",
        "/",
        "/",
        "18600",
        "2.20",
        "0.90",
        "0.78",
        "12400",
        "13600",
        "/",
        "/",
        "17800",
        "2.00",
        "0.90",
        "0.78",
        "11700",
        "12800",
        "/",
        "/",
        "16900",
        "1.80",
        "0.90",
        "0.78",
        "8800",
        "10700",
        "/",
        "/",
        "15800",
        "SZ-14",
        "漂流岛",
        "2.40",
        "1.00",
        "0.78",
        "11500",
        "12800",
        "/",
        "/",
        "17800",
        "2.40",
        "0.90",
        "10800",
        "12000",
        "/",
        "/",
        "16600",
        "2.20",
        "0.90",
        "10400",
        "11600",
        "/",
        "/",
        "15800",
        "2.00",
        "0.90",
        "9700",
        "10800",
        "/",
        "/",
        "14900",
        "1.80",
        "0.90",
        "6800",
        "8700",
        "/",
        "/",
        "13800",
        "漂流岛Y",
        "2.40",
        "1.00",
        "0.78",
        "12500",
        "13800",
        "/",
        "/",
        "18800",
        "2.40",
        "0.90",
        "11800",
        "13000",
        "/",
        "/",
        "17600",
        "2.20",
        "0.90",
        "11400",
        "12600",
        "/",
        "/",
        "16800",
        "2.00",
        "0.90",
        "10700",
        "11800",
        "/",
        "/",
        "15900",
        "1.80",
        "0.90",
        "7800",
        "9700",
        "/",
        "/",
        "14800",
        "SZ-18",
        "挂墙桌",
        "0.60",
        "0.40",
        "0.146",
        "1500",
        "1750",
        "1750",
        "1950",
        "2250",
        "1.00",
        "2000",
        "2350",
        "2350",
        "2700",
        "3150",
        "1.20",
        "2600",
        "2950",
        "2950",
        "3400",
        "3950",
        "1.60",
        "3700",
        "4250",
        "4250",
        "4850",
        "5650",
        "SZ-01",
        "罗胖书桌",
        "1.20",
        "0.60",
        "0.78",
        "4100",
        "4600",
        "4600",
        "5280",
        "6180",
        "1.40",
        "4600",
        "5300",
        "5300",
        "6380",
        "7180",
        "1.60",
        "0.70",
        "5100",
        "5800",
        "5800",
        "7280",
        "9180",
        "1.80",
        "0.80",
        "5600",
        "6800",
        "6800",
        "8580",
        "11000",
        "2.00",
        "6600",
        "8300",
        "8300",
        "9900",
        "14000",
        "SZ-02",
        "经典双屉书桌",
        "1.20",
        "0.60",
        "0.78",
        "3080",
        "3580",
        "3580",
        "4280",
        "5080",
        "1.40",
        "3380",
        "4080",
        "4080",
        "4780",
        "5680",
        "1.60",
        "0.70",
        "4080",
        "4880",
        "4880",
        "5780",
        "6880",
        "SZ-05",
        "经典儿童多屉书桌",
        "1.20",
        "0.60",
        "0.83",
        "5300",
        "6200",
        "6200",
        "7000",
        "8580",
        "1.40",
        "5800",
        "6900",
        "6900",
        "8080",
        "9580",
        "1.60",
        "6300",
        "7400",
        "7400",
        "8980",
        "11580",
        "1.80",
        "6800",
        "8400",
        "8400",
        "10280",
        "13400",
        "SZ-07",
        "并立书桌",
        "2.40",
        "0.60",
        "0.78",
        "9380",
        "11480",
        "11480",
        "13980",
        "15480",
        "SZ-10",
        "简美书桌",
        "1.20",
        "0.65",
        "0.78",
        "4800",
        "5500",
        "5500",
        "6380",
        "6600",
        "SZ-13",
        "漂浮书桌",
        "1.60",
        "0.80",
        "0.78",
        "5700",
        "6600",
        "6600",
        "8180",
        "10380",
        "1.80",
        "0.90",
        "6200",
        "7600",
        "7600",
        "9380",
        "12200",
        "2.00",
        "0.90",
        "7200",
        "9100",
        "9100",
        "10780",
        "15200",
        "1.40",
        "0.60",
        "4600",
        "5300",
        "5300",
        "6380",
        "7180",
        "1.60",
        "0.70",
        "5100",
        "5800",
        "5800",
        "7280",
        "9180",
        "1.80",
        "0.80",
        "5600",
        "6800",
        "6800",
        "8580",
        "11000",
        "2.00",
        "6600",
        "8300",
        "8300",
        "9900",
        "14000",
        "SZG-11",
        "经典书桌柜",
        "1.20",
        "0.65",
        "2.00",
        "8900",
        "10100",
        "10100",
        "12000",
        "13600",
        "SZG-13",
        "经典书桌与吊柜",
        "1.20",
        "0.60",
        "2.06",
        "5300",
        "6200",
        "6200",
        "6980",
        "8580",
        "3680",
        "4180",
        "4180",
        "4980",
        "5680",
        "4480",
        "4980",
        "4980",
        "5980",
        "6680",
        "平板门纹理连续＞0.9m时按平板门单价计算",
        "SZG-15",
        "经典转角书桌柜",
        "1.20",
        "1.40",
        "2.04",
        "10000",
        "12000",
        "12000",
        "14000",
        "15000",
        "SZG-13经典书桌与吊柜：红色：书桌价格；绿色：吊柜开放单价；蓝色：吊柜带门单价"
      ]
    },
    {
      "heading": "7.6椅子",
      "content": [
        "编号",
        "名称",
        "图示",
        "玫瑰木",
        "樱桃木",
        "白蜡木",
        "白橡木",
        "黑胡桃",
        "编号",
        "名称",
        "图示",
        "玫瑰木",
        "樱桃木",
        "白蜡木",
        "白橡木",
        "黑胡桃",
        "YZ-01",
        "罗胖椅",
        "1200",
        "1600",
        "1600",
        "1700",
        "1800",
        "YZ-06",
        "主咖大座",
        "2100",
        "2600",
        "2600",
        "2900",
        "3500",
        "YZ-02",
        "新Y椅",
        "1800",
        "2000",
        "2000",
        "2200",
        "2600",
        "YZ-07",
        "主咖巨大座",
        "2300",
        "3400",
        "3400",
        "3800",
        "4500",
        "YZ-03",
        "高背罗胖椅",
        "1200",
        "1600",
        "1600",
        "1700",
        "1800",
        "YZ-08",
        "江口椅",
        "2100",
        "2600",
        "2600",
        "2900",
        "3500",
        "YZ-05",
        "广岛椅",
        "1800",
        "2000",
        "2000",
        "2200",
        "2600",
        "YZ-09",
        "蝙蝠椅",
        "1800",
        "2000",
        "2000",
        "2200",
        "2600",
        "YZ-10",
        "新夏克椅",
        "1800",
        "2000",
        "2000",
        "2200",
        "2600",
        "YZ-12",
        "长滩h椅",
        "960",
        "980",
        "980",
        "1280",
        "1380",
        "YZ-11",
        "长滩n椅",
        "960",
        "980",
        "980",
        "1280",
        "1380",
        "YZ-13",
        "金属靠背椅",
        "890",
        "910",
        "910",
        "1180",
        "1280"
      ]
    },
    {
      "heading": "7.7 凳子",
      "content": [
        "编号",
        "名称",
        "图示",
        "长/m",
        "宽/m",
        "高/m",
        "玫瑰木",
        "樱桃木",
        "白蜡木",
        "白橡木",
        "黑胡桃",
        "TD-01",
        "罗胖条凳",
        "1.4",
        "0.28",
        "0.43",
        "1200",
        "1800",
        "1800",
        "2000",
        "2200",
        "TD-04",
        "美人凳",
        "0.5",
        "0.3",
        "0.43",
        "800",
        "1000",
        "1000",
        "1100",
        "1200",
        "DZ-01",
        "圆凳凳",
        "0.39",
        "0.39",
        "0.43",
        "880",
        "980",
        "980",
        "1030",
        "1080",
        "TD-05",
        "漂流条凳",
        "1.4",
        "0.3",
        "0.43",
        "/",
        "3180",
        "/",
        "/",
        "3580",
        "1.6",
        "0.3",
        "0.43",
        "/",
        "3380",
        "/",
        "/",
        "4080",
        "TD-06",
        "长滩条凳",
        "1.4",
        "0.3",
        "0.43",
        "/",
        "3480",
        "/",
        "/",
        "3880",
        "1.6",
        "0.3",
        "0.43",
        "/",
        "3680",
        "/",
        "/",
        "4380",
        "DZ-02",
        "方凳",
        "0.39",
        "0.39",
        "0.43",
        "550",
        "670",
        "670",
        "750",
        "820"
      ]
    },
    {
      "heading": "7.8儿童床",
      "content": [
        "儿童上下床（以下图为例）",
        "样式",
        "ETC-01经典挂梯上下床-架式",
        "ETC-02经典梯柜上下床-箱体",
        "ETC-11城堡挂梯上下床-架式",
        "ETC-12城堡梯柜上下床-架式",
        "尺寸"
      ]
    },
    {
      "heading": "0.9*1.2",
      "content": []
    },
    {
      "heading": "1.2*1.2",
      "content": []
    },
    {
      "heading": "0.9*1.2",
      "content": []
    },
    {
      "heading": "1.2*1.2",
      "content": []
    },
    {
      "heading": "1.2*1.2",
      "content": [
        "玫瑰木",
        "9500",
        "10380",
        "13900",
        "13660",
        "16050",
        "樱桃木",
        "12520",
        "13700",
        "19230",
        "17170",
        "21110",
        "白蜡木",
        "12520",
        "13700",
        "19230",
        "17170",
        "21110",
        "白橡木",
        "15610",
        "17080",
        "23980",
        "21410",
        "26330",
        "黑胡桃",
        "18660",
        "20420",
        "28660",
        "26000",
        "31870"
      ]
    },
    {
      "heading": "1.非标品按非标儿童床报价方案执行。",
      "content": []
    },
    {
      "heading": "2.标红款为特价款，特价款不可做任何更改，如有任何更改均按常规价格计价。",
      "content": [
        "ETC-01经典挂梯上下床-架式                     ETC-02经典梯柜上下床-箱体         ETC-11城堡挂梯上下床-架式    ETC-12城堡梯柜上下床-架式"
      ]
    },
    {
      "heading": "0.9*1.2               1.2*1.2                    0.9*1.2                         1.2*1.2                1.2*1.2",
      "content": [
        "其他儿童床",
        "编号",
        "名称",
        "图示",
        "长/m",
        "宽/m",
        "高/m",
        "玫瑰木",
        "樱桃木",
        "白蜡木",
        "白橡木",
        "黑胡桃",
        "ETC-03",
        "儿童床书柜伴床",
        "1.2",
        "2",
        "50-100",
        "12800",
        "14000",
        "14000",
        "15400",
        "/",
        "ETC-05",
        "公主床",
        "1.5",
        "2",
        "50-100",
        "5500",
        "6800",
        "6800",
        "7900",
        "9800",
        "1.8",
        "2",
        "6200",
        "7200",
        "7200",
        "9000",
        "11800",
        "ETC-06",
        "单人床1",
        "1.2",
        "2",
        "50-100",
        "4500",
        "5800",
        "5800",
        "6800",
        "8800",
        "ETC-07",
        "单人床2",
        "1.2",
        "2",
        "50-100",
        "4500",
        "5800",
        "5800",
        "6800",
        "8800",
        "ETC-08",
        "ins儿童床",
        "1.2",
        "2",
        "100-200",
        "5500",
        "6800",
        "6800",
        "7480",
        "9800",
        "1.5",
        "7200",
        "8200",
        "8200",
        "9020",
        "12000",
        "ETC-09",
        "糖果儿童床",
        "1.5",
        "2",
        "50-150",
        "8200",
        "9200",
        "9200",
        "11200",
        "13800",
        "1.8",
        "2",
        "9280",
        "10800",
        "10800",
        "13800",
        "16980",
        "ETC-10",
        "积木上下床",
        "1",
        "2",
        "50-100",
        "8500",
        "9600",
        "9600",
        "10600",
        "11300",
        "1"
      ]
    },
    {
      "heading": "7.9床榻",
      "content": [
        "编号",
        "名称",
        "图示",
        "宽度/m",
        "长度/m",
        "玫瑰木",
        "樱桃木",
        "白蜡木",
        "白橡木",
        "黑胡桃",
        "JSC-01",
        "抛物线架式床",
        "1.5",
        "2",
        "6900",
        "8600",
        "8600",
        "10100",
        "11600",
        "1.8",
        "2",
        "7600",
        "9000",
        "9000",
        "11000",
        "12980",
        "JSC-02",
        "悬浮",
        "架式床",
        "1.5",
        "2",
        "5500",
        "6800",
        "6800",
        "8000",
        "9800",
        "1.8",
        "2",
        "6200",
        "7200",
        "7200",
        "9000",
        "11800",
        "JSC-03",
        "经典",
        "架式床01",
        "1.5",
        "2",
        "5500",
        "6800",
        "6800",
        "8000",
        "9800",
        "1.8",
        "2",
        "6200",
        "7200",
        "7200",
        "9000",
        "11800",
        "JSC-04",
        "梳背",
        "架式床",
        "1.5",
        "2",
        "5500",
        "6800",
        "6800",
        "8000",
        "9800",
        "1.8",
        "2",
        "6200",
        "7200",
        "7200",
        "9000",
        "11800",
        "JSC-05-1",
        "支腿架式床",
        "1.5",
        "2",
        "5180",
        "6180",
        "6180",
        "7180",
        "8980",
        "1.8",
        "2",
        "5880",
        "6880",
        "6880",
        "7880",
        "9880",
        "JSC-06",
        "华夫格软包架式床",
        "1.5",
        "2",
        "5180",
        "6180",
        "6180",
        "7180",
        "8980",
        "1.8",
        "2",
        "5880",
        "6880",
        "6880",
        "7880",
        "9880",
        "JSC-07",
        "欧包软靠床",
        "1.5",
        "2",
        "5180",
        "6180",
        "6180",
        "7180",
        "8980",
        "1.8",
        "2",
        "5880",
        "6880",
        "6880",
        "7880",
        "9880",
        "XTC-01",
        "经典",
        "箱体床",
        "1.5",
        "2",
        "7200",
        "8200",
        "8200",
        "9900",
        "12800",
        "1.8",
        "2",
        "8200",
        "8800",
        "8800",
        "10600",
        "15280",
        "XTC-02",
        "悬浮",
        "箱体床",
        "1.5",
        "2",
        "8200",
        "9200",
        "9200",
        "11200",
        "13800",
        "1.8",
        "2",
        "9280",
        "10800",
        "10800",
        "13880",
        "16980",
        "XTC-02-1",
        "悬浮",
        "箱体床(支腿优化版)",
        "1.5",
        "2",
        "7800",
        "8800",
        "8800",
        "10800",
        "13400",
        "1.8",
        "2",
        "8880",
        "10400",
        "10400",
        "12600",
        "15580",
        "XTC-03",
        "飘飘家的藤编床",
        "1.5",
        "2",
        "7800",
        "8800",
        "8800",
        "10800",
        "13400",
        "1.8",
        "2",
        "8880",
        "10400",
        "10400",
        "12600",
        "15580",
        "XTC-04-1",
        "支腿箱体床",
        "1.5",
        "2",
        "7800",
        "8800",
        "8800",
        "10800",
        "13400",
        "1.8",
        "2",
        "8880",
        "10400",
        "10400",
        "12600",
        "15580",
        "XTC-05",
        "华夫格软包箱体床",
        "1.5",
        "2",
        "7200",
        "8200",
        "8200",
        "9900",
        "12800",
        "1.8",
        "2",
        "8200",
        "8800",
        "8800",
        "10600",
        "15280",
        "MSC-01",
        "经典",
        "美式床01",
        "箱体",
        "1.5",
        "2",
        "10580",
        "11980",
        "/",
        "12980",
        "14980",
        "1.8",
        "2",
        "11580",
        "12980",
        "/",
        "14680",
        "16680",
        "MSC-02",
        "经典",
        "美式床02",
        "架式",
        "1.5",
        "2",
        "8980",
        "9980",
        "/",
        "10980",
        "12980",
        "1.8",
        "2",
        "10580",
        "11980",
        "/",
        "12980",
        "14980",
        "箱体",
        "1.5",
        "2",
        "11580",
        "12980",
        "/",
        "13980",
        "15980",
        "1.8",
        "2",
        "12580",
        "13980",
        "/",
        "15680",
        "17680"
      ]
    }
  ]
}
